pms5003_async/__init__.py
pms5003_async-0.0.1.dev2.dist-info/LICENSE
pms5003_async-0.0.1.dev2.dist-info/METADATA
pms5003_async-0.0.1.dev2.dist-info/WHEEL
pms5003_async-0.0.1.dev2.dist-info/entry_points.txt
pms5003_async-0.0.1.dev2.dist-info/top_level.txt
pms5003_async-0.0.1.dev2.dist-info/RECORD
